micronet/__init__.py
micronet/micronet.py
micronet/Protocols/Application.py
micronet/Protocols/Network.py
micronet/Protocols/Network_interface.py
micronet/Protocols/Transport.py
micronet/Protocols/__init__.py
micronet/Protocols/base.py
micronet/drivers/__init__.py
micronet/drivers/enc28j60/__init__.py
micronet/drivers/enc28j60/enc28j60.py
micropython_micronet-0.1.0.dist-info/METADATA
micropython_micronet-0.1.0.dist-info/WHEEL
micropython_micronet-0.1.0.dist-info/top_level.txt
micropython_micronet-0.1.0.dist-info/RECORD
