Metadata-Version: 2.1
Name: micropython-micronet
Version: 0.1.0
Summary: MicroPython library for networking
Home-page: https://github.com/yeranosyanvahan/micronet
Author: Vahan Yeranosyan
Author-email: vahan@yeranosyanvahan.com
Maintainer: Vahan Yeranosyan
Maintainer-email: vahan@yeranosyanvahan.com
License: MIT
Classifier: Development Status :: 2 - Pre-Alpha
Classifier: Intended Audience :: Developers
Classifier: Programming Language :: Python :: Implementation :: MicroPython
Classifier: License :: OSI Approved :: MIT License
